{
  "id": "com.megaradio.tv",
  "version": "1.0.0",
  "vendor": "Mega Radio",
  "type": "web",
  "main": "index.html",
  "title": "Mega Radio",
  "icon": "images/icon-80.png",
  "largeIcon": "images/icon-130.png",
  "bgImage": "images/bg.png",
  "iconColor": "#ff4199",
  "appDescription": "Global Radio Streaming for LG webOS TV - Access thousands of radio stations from 238+ countries",
  "resolution": "1920x1080",
  "disallowScrollingInMainWindow": true,
  "transparent": false,
  "v2": {
    "displayAffinity": "main"
  }
}
